<?xml version="1.0" encoding="UTF-8"?>
<bilety xmlns="http://xml.mimuw.edu.pl/jm364533/tgnamespc">
  <bilet>
    <trasa>
      <start>
        <nazwa>Warszawa</nazwa>
      </start>
      <koniec>
        <nazwa>Wroclaw</nazwa>
      </koniec>
      <numerPociagu>123456</numerPociagu>
    </trasa>
    <miejsce>10</miejsce>
    <odcinki>
      <odcinek>warszawa-lodz</odcinek>
    </odcinki>
    <data>2017-01-01</data>
    <cena>70</cena>
    <wartoscZnizki>0.5</wartoscZnizki>
  </bilet>
  <bilet>
    <trasa>
      <start>
        <nazwa>Warszawa</nazwa>
      </start>
      <koniec>
        <nazwa>Wroclaw</nazwa>
      </koniec>
      <numerPociagu>123456</numerPociagu>
    </trasa>
    <miejsce>10</miejsce>
    <odcinki>
      <odcinek>lodz-wroclaw</odcinek>
    </odcinki>
    <data>2017-01-01</data>
    <cena>70</cena>
    <wartoscZnizki>0.5</wartoscZnizki>
  </bilet>
  <bilet>
    <trasa>
      <start>
        <nazwa>Warszawa</nazwa>
      </start>
      <koniec>
        <nazwa>Wroclaw</nazwa>
      </koniec>
      <numerPociagu>123456</numerPociagu>
    </trasa>
    <miejsce>1</miejsce>
    <odcinki>
      <odcinek>warszawa-lodz</odcinek>
      <odcinek>lodz-wroclaw</odcinek>
    </odcinki>
    <data>2017-01-01</data>
    <cena>70</cena>
    <wartoscZnizki>0.5</wartoscZnizki>
  </bilet>
  <bilet>
    <trasa>
      <start>
        <nazwa>Warszawa</nazwa>
      </start>
      <koniec>
        <nazwa>Lodz</nazwa>
      </koniec>
      <numerPociagu>123456</numerPociagu>
    </trasa>
    <miejsce>2</miejsce>
    <odcinki>
      <odcinek>warszawa-lodz</odcinek>
    </odcinki>
    <data>2017-01-01</data>
    <cena>70</cena>
    <wartoscZnizki>0.5</wartoscZnizki>
  </bilet>
  <bilet>
    <trasa>
      <start>
        <nazwa>Lodz</nazwa>
      </start>
      <koniec>
        <nazwa>Wroclaw</nazwa>
      </koniec>
      <numerPociagu>123456</numerPociagu>
    </trasa>
    <miejsce>3</miejsce>
    <odcinki>
      <odcinek>lodz-wroclaw</odcinek>
    </odcinki>
    <data>2017-01-01</data>
    <cena>70</cena>
    <wartoscZnizki>1</wartoscZnizki>
  </bilet>
</bilety>